ompr/__init__.py
ompr/helpers.py
ompr/runner.py
ompr/simple.py
ompr-1.6.3.dist-info/METADATA
ompr-1.6.3.dist-info/WHEEL
ompr-1.6.3.dist-info/top_level.txt
ompr-1.6.3.dist-info/RECORD
