Metadata-Version: 2.1
Name: ompr
Version: 1.6.3
Summary: Object based Multi-Processing Runner
Home-page: https://github.com/piteren/ompr.git
Author: Piotr Niewinski
Author-email: pioniewinski@gmail.com
License: MIT
Requires-Dist: psutil
Requires-Dist: pypaq
